model/__init__.py
model/column.py
model/data_access_request.py
model/data_domain.py
model/data_domain_user.py
model/data_user.py
model/database.py
model/glue_connection.py
model/jobs_log.py
model/table.py
model/table_analytics.py
model/table_raw.py
model/table_trusted.py
repository/__init__.py
repository/approver_repository.py
repository/column_repository.py
repository/data_access_request_repository.py
repository/data_domain_repository.py
repository/data_domain_user_repository.py
repository/data_user_repository.py
repository/database_repository.py
repository/glue_connection_repository.py
repository/jobs_log_repository.py
repository/policy_repository.py
repository/table_analytics_repository.py
repository/table_raw_repository.py
repository/table_repository.py
repository/table_trusted_repository.py
schema/__init__.py
schema/data_user_schema.py
schema/ingestion_object_schema.py
schema/process_schema.py
schema/upload_schema.py
service/__init__.py
service/analytics_job_service.py
service/column_service.py
service/data_access_request_service.py
service/data_user_service.py
service/database_service.py
service/domain_service.py
service/glue_connection_service.py
service/ingestion_service.py
service/jobs_log_service.py
service/table_service.py
service/upload_service.py
util/__init__.py
util/auth.py
util/client.py
util/email.py
util/inconsistence_exception.py
util/not_found_exception.py
util/unauthorized_exception.py
datalakecore-0.1.6.dist-info/METADATA
datalakecore-0.1.6.dist-info/WHEEL
datalakecore-0.1.6.dist-info/top_level.txt
datalakecore-0.1.6.dist-info/RECORD
