Metadata-Version: 2.1
Name: datalakecore
Version: 0.1.6
Summary: Biblioteca Core
Author: Data Platform Team
Author-email: data.platform@sankhya.com.br
Classifier: Programming Language :: Python :: 3
Classifier: License :: OSI Approved :: MIT License
Classifier: Operating System :: OS Independent
Requires-Python: >=3.12
